apphub/__init__.py
apphub/apphub.py
apphub/decorators.py
apphub/exceptions.py
apphub/globals.py
apphub/utils.py
apphub-2.1.0.dist-info/METADATA
apphub-2.1.0.dist-info/WHEEL
apphub-2.1.0.dist-info/top_level.txt
apphub-2.1.0.dist-info/RECORD
