Metadata-Version: 2.1
Name: apphub
Version: 2.1.0
Summary: Swimlane Apphub API Package
Home-page: UNKNOWN
Author: Swimlane
Author-email: info@swimlane.com
License: UNKNOWN
Keywords: dev,development
Platform: UNKNOWN
Classifier: Programming Language :: Python :: 3
Classifier: Programming Language :: Python
Requires-Python: >=3.6, <4
Requires-Dist: requests (==2.26.0)
Requires-Dist: pendulum (==2.1.2)
